{
  "3300100": { "resumo": "", "historiaCompleta": [] },
  "3300159": { "resumo": "", "historiaCompleta": [] },
  "3300209": { "resumo": "", "historiaCompleta": [] },
  "3300225": { "resumo": "", "historiaCompleta": [] },
  "3300233": { "resumo": "", "historiaCompleta": [] },
  "3300258": { "resumo": "", "historiaCompleta": [] },
  "3300308": { "resumo": "", "historiaCompleta": [] },
  "3300407": { "resumo": "", "historiaCompleta": [] },
  "3300456": { "resumo": "", "historiaCompleta": [] },
  "3300506": { "resumo": "", "historiaCompleta": [] },
  "3300605": { "resumo": "", "historiaCompleta": [] },
  "3300704": { "resumo": "", "historiaCompleta": [] },
  "3300803": { "resumo": "", "historiaCompleta": [] },
  "3300902": { "resumo": "", "historiaCompleta": [] },
  "3300936": { "resumo": "", "historiaCompleta": [] },
  "3300951": { "resumo": "", "historiaCompleta": [] },
  "3301009": { "resumo": "", "historiaCompleta": [] },
  "3301108": { "resumo": "", "historiaCompleta": [] },
  "3301157": { "resumo": "", "historiaCompleta": [] },
  "3301207": { "resumo": "", "historiaCompleta": [] },
  "3301306": { "resumo": "", "historiaCompleta": [] },
  "3301405": { "resumo": "", "historiaCompleta": [] },
  "3301504": { "resumo": "", "historiaCompleta": [] },
  "3301603": { "resumo": "", "historiaCompleta": [] },
  "3301702": { "resumo": "", "historiaCompleta": [] },
  "3301801": { "resumo": "", "historiaCompleta": [] },
  "3301850": { "resumo": "", "historiaCompleta": [] },
  "3301876": { "resumo": "", "historiaCompleta": [] },
  "3301900": { "resumo": "", "historiaCompleta": [] },
  "3302007": { "resumo": "", "historiaCompleta": [] },
  "3302056": { "resumo": "", "historiaCompleta": [] },
  "3302106": { "resumo": "", "historiaCompleta": [] },
  "3302205": { "resumo": "", "historiaCompleta": [] },
  "3302254": { "resumo": "", "historiaCompleta": [] },
  "3302270": { "resumo": "", "historiaCompleta": [] },
  "3302304": { "resumo": "", "historiaCompleta": [] },
  "3302403": { "resumo": "", "historiaCompleta": [] },
  "3302452": { "resumo": "", "historiaCompleta": [] },
  "3302502": { "resumo": "", "historiaCompleta": [] },
  "3302601": { "resumo": "", "historiaCompleta": [] },
  "3302700": { "resumo": "", "historiaCompleta": [] },
  "3302809": { "resumo": "", "historiaCompleta": [] },
  "3302858": { "resumo": "", "historiaCompleta": [] },
  "3302908": { "resumo": "", "historiaCompleta": [] },
  "3303005": { "resumo": "", "historiaCompleta": [] },
  "3303104": { "resumo": "", "historiaCompleta": [] },
  "3303203": { "resumo": "", "historiaCompleta": [] },
  "3303302": {
    "resumo": "Niterói, a \"Cidade Sorriso\", é a única cidade do Brasil fundada por um líder indígena — o cacique Arariboia, em 1573. Chegou a ser capital do Rio de Janeiro entre 1835 e 1975 e hoje tem o maior IDH do estado.",
    "historiaCompleta": [
      "Fundada em 22 de novembro de 1573 pelo cacique temiminó Arariboia — recompensado com terras por ajudar os portugueses a expulsar os franceses da Baía de Guanabara —, Niterói é a única cidade do Brasil fundada por um líder indígena, e não por colonizadores europeus. Seu nome vem do tupi (Nictheroy) e significa \"água escondida\".",
      "Em 1819 virou Vila Real da Praia Grande; em 1834 foi escolhida capital da Província do Rio de Janeiro e, em 1835, rebatizada Niterói. Bombardeada durante a Revolta da Armada em 1890, chegou a perder o posto de capital para Petrópolis por alguns anos, recuperando o título em 1903. Com a fusão dos estados da Guanabara e do Rio de Janeiro em 1975, Niterói perdeu definitivamente o status de capital para a cidade do Rio.",
      "A Ponte Rio-Niterói, inaugurada em 1974, tem 13,29 km e é a maior ponte do Hemisfério Sul. O apelido \"Cidade Sorriso\", da década de 1950, celebra a hospitalidade dos niteroienses e a beleza das praias tranquilas da baía — hoje a cidade também lidera o Índice de Desenvolvimento Humano (IDH) do estado do Rio de Janeiro."
    ]
  },
  "3303401": { "resumo": "", "historiaCompleta": [] },
  "3303500": { "resumo": "", "historiaCompleta": [] },
  "3303609": { "resumo": "", "historiaCompleta": [] },
  "3303708": { "resumo": "", "historiaCompleta": [] },
  "3303807": { "resumo": "", "historiaCompleta": [] },
  "3303856": { "resumo": "", "historiaCompleta": [] },
  "3303906": { "resumo": "", "historiaCompleta": [] },
  "3303955": { "resumo": "", "historiaCompleta": [] },
  "3304003": { "resumo": "", "historiaCompleta": [] },
  "3304102": { "resumo": "", "historiaCompleta": [] },
  "3304110": { "resumo": "", "historiaCompleta": [] },
  "3304128": { "resumo": "", "historiaCompleta": [] },
  "3304144": { "resumo": "", "historiaCompleta": [] },
  "3304151": { "resumo": "", "historiaCompleta": [] },
  "3304201": { "resumo": "", "historiaCompleta": [] },
  "3304300": { "resumo": "", "historiaCompleta": [] },
  "3304409": { "resumo": "", "historiaCompleta": [] },
  "3304508": { "resumo": "", "historiaCompleta": [] },
  "3304524": { "resumo": "", "historiaCompleta": [] },
  "3304557": { "resumo": "", "historiaCompleta": [] },
  "3304607": { "resumo": "", "historiaCompleta": [] },
  "3304706": { "resumo": "", "historiaCompleta": [] },
  "3304755": { "resumo": "", "historiaCompleta": [] },
  "3304805": { "resumo": "", "historiaCompleta": [] },
  "3304904": { "resumo": "", "historiaCompleta": [] },
  "3305000": { "resumo": "", "historiaCompleta": [] },
  "3305109": { "resumo": "", "historiaCompleta": [] },
  "3305133": { "resumo": "", "historiaCompleta": [] },
  "3305158": { "resumo": "", "historiaCompleta": [] },
  "3305208": { "resumo": "", "historiaCompleta": [] },
  "3305307": { "resumo": "", "historiaCompleta": [] },
  "3305406": { "resumo": "", "historiaCompleta": [] },
  "3305505": { "resumo": "", "historiaCompleta": [] },
  "3305554": { "resumo": "", "historiaCompleta": [] },
  "3305604": { "resumo": "", "historiaCompleta": [] },
  "3305703": { "resumo": "", "historiaCompleta": [] },
  "3305752": { "resumo": "", "historiaCompleta": [] },
  "3305802": { "resumo": "", "historiaCompleta": [] },
  "3305901": { "resumo": "", "historiaCompleta": [] },
  "3306008": { "resumo": "", "historiaCompleta": [] },
  "3306107": { "resumo": "", "historiaCompleta": [] },
  "3306156": { "resumo": "", "historiaCompleta": [] },
  "3306206": { "resumo": "", "historiaCompleta": [] },
  "3306305": { "resumo": "", "historiaCompleta": [] }
}
